featcat_mcp_demo/__init__.py
featcat_mcp_demo-0.1.0.dist-info/WHEEL
featcat_mcp_demo-0.1.0.dist-info/entry_points.txt
featcat_mcp_demo-0.1.0.dist-info/METADATA
featcat_mcp_demo-0.1.0.dist-info/RECORD
