Metadata-Version: 2.3
Name: featcat-mcp-demo
Version: 0.1.0
Summary: Add your description here
Author: fatcat
Author-email: fatcat <fatcat@gmail.com>
Requires-Dist: mcp[cli]>=1.12.4
Requires-Python: >=3.13
